[{"key": "cinema_ticket", "values": [{"label": "Al-khubar, Saudi Arabia", "value": 0.9331715835921774}, {"label": "Nha Trang, Vietnam", "value": 0.8591681673658957}, {"label": "Miskolc, Hungary", "value": 0.8298353468365984}, {"label": "Szolnok, Hungary", "value": 0.8298353468365984}, {"label": "Czestochowa, Poland", "value": 0.809141621607103}, {"label": "Batumi, Ajara, Georgia", "value": 0.8073394495412844}, {"label": "Kragujevac, Serbia", "value": 0.8072174738841406}, {"label": "Sana (Sanaa), Yemen", "value": 0.7988791820940722}, {"label": "Sfax, Tunisia", "value": 0.6640509698962453}, {"label": "Al-khubar, Saudi Arabia", "value": 0.5332409049098157}]}]