[{"key": "cinema_ticket", "values": [{"label": "Tamuning, Guam", "value": 6.613867865546327}, {"label": "Tumon, Guam", "value": 6.613867865546327}, {"label": "Tahiti, French Polynesia", "value": 3.99074713819532}, {"label": "Sunshine Coast, Australia", "value": 3.567889277439212}, {"label": "Gosford, Australia", "value": 3.3361169424874517}, {"label": "Parramatta, Australia", "value": 3.1605318402512697}, {"label": "Wollongong, Australia", "value": 3.1429733300276514}, {"label": "Newcastle, Australia", "value": 3.1020034728392094}, {"label": "Orange, NSW, Australia", "value": 3.060313266513388}, {"label": "Canberra, Australia", "value": 2.963876525746746}]}]